pytradecn/__init__.py
pytradecn/email.py
pytradecn/error.py
pytradecn/logger.py
pytradecn/prompt.py
pytradecn/uiacontrol.py
pytradecn/client/__init__.py
pytradecn/client/baseclient.py
pytradecn/client/brokera.py
pytradecn/client/brokerb.py
pytradecn/control/__init__.py
pytradecn/control/baseuiawrapper.py
pytradecn/control/wrappersa.py
pytradecn/control/wrappersb.py
pytradecn/control/wrappersc.py
pytradecn/engine/__init__.py
pytradecn/engine/baseengine.py
pytradecn/engine/enginesa.py
pytradecn/engine/enginesb.py
pytradecn/model/__init__.py
pytradecn/model/basemodel.py
pytradecn/model/modelsa.py
pytradecn/model/modelsb.py
pytradecn/template/__init__.py
pytradecn/template/basetemplate.py
pytradecn/utils/__init__.py
pytradecn/utils/general.py
pytradecn/utils/ocr.py
pytradecn-0.0.9.dist-info/LICENCE
pytradecn-0.0.9.dist-info/METADATA
pytradecn-0.0.9.dist-info/WHEEL
pytradecn-0.0.9.dist-info/top_level.txt
pytradecn-0.0.9.dist-info/RECORD
