Metadata-Version: 2.1
Name: pytradecn
Version: 0.0.9
Summary: a securities client automated trading model based on customized factory pattern design
Author-email: shuideshui <41715399@qq.com>
License: MIT
Project-URL: Homepage, https://github.com/sxwyh/pytradecn
Project-URL: Bug Tracker, https://github.com/sxwyh/pytradecn/issues
Keywords: automated,trade,broker,china,中国,券商客户端,自动化交易,银河证券
Classifier: Programming Language :: Python :: 3
Classifier: License :: OSI Approved :: MIT License
Classifier: Natural Language :: Chinese (Simplified)
Classifier: Environment :: Win32 (MS Windows)
Requires-Python: >=3.9
License-File: LICENCE
Requires-Dist: pillow
Requires-Dist: pywinauto >=0.6.8
